garden/worker.py
globe/api.py
globe/aws_server.py
globe/sim_server.py
globalgarden-0.1.0.dist-info/WHEEL
globalgarden-0.1.0.dist-info/METADATA
globalgarden-0.1.0.dist-info/RECORD
