Metadata-Version: 2.1
Name: globalgarden
Version: 0.1.0
Summary: distributed non-differentiable optimization
License: MIT
Author: Ilya Kamen
Author-email: ikamenshchikov@gmail.com
Requires-Python: >=3.6,<4.0
Classifier: License :: OSI Approved :: MIT License
Classifier: Programming Language :: Python :: 3
Classifier: Programming Language :: Python :: 3.6
Classifier: Programming Language :: Python :: 3.7
Classifier: Programming Language :: Python :: 3.8
Classifier: Programming Language :: Python :: 3.9
Requires-Dist: blackopt
Requires-Dist: loguru
